thecatapi/__init__.py
thecatapi/base.py
thecatapi/breeds.py
thecatapi/facts.py
thecatapi/favourites.py
thecatapi/images.py
thecatapi/thecatapi.py
thecatapi/votes.py
thecatapi/tests/__init__.py
thecatapi/tests/test_images.py
thecatapi_sdk-0.0.1.dist-info/LICENSE
thecatapi_sdk-0.0.1.dist-info/METADATA
thecatapi_sdk-0.0.1.dist-info/WHEEL
thecatapi_sdk-0.0.1.dist-info/top_level.txt
thecatapi_sdk-0.0.1.dist-info/RECORD
