Metadata-Version: 2.1
Name: thecatapi-sdk
Version: 0.0.1
Summary: Python wrapper for making secure requests to TheCatAPI
Home-page: https://github.com/ize-302/thecatapi-py-sdk
Author: Adavize Hassan
Author-email: adavizeozorku@gmail.com
Project-URL: Source, https://github.com/ize-302/thecatapi-py-sdk
Requires-Python: >=3.12
License-File: LICENSE
Requires-Dist: requests
